Workbook

Sheet Роли
A1: NetShield — распределение ролей и прогресс
A2: Имена вводятся в столбце B (синий). Счётчики считаются по листу «Задачи».
A4: Роль | B4: Имя участника | C4: Зона ответственности | D4: Папки репозитория | E4: Задач | F4: В работе | G4: Готово | H4: Прогресс | I4: Задачи-недели | J4: Подробных пунктов | K4: В работе (подр.) | L4: Готово (подр.) | M4: Прогресс (подр.)
A5: Человек 1 | C5: Linux, сеть, firewall, Rule Manager, скрипты безопасности, стенд, замеры производительности | D5: scripts/, app/firewall/, deploy/, lab/ | E5: =COUNTIF(Задачи!$B$5:$B$48,A5) -> 14 | F5: =COUNTIFS(Задачи!$B$5:$B$48,A5,Задачи!$H$5:$H$48,"В работе") -> 0 | G5: =COUNTIFS(Задачи!$B$5:$B$48,A5,Задачи!$H$5:$H$48,"Готово") -> 0 | H5: =IF(E5=0,0,G5/E5) -> 0 | I5: =SUMIF(Задачи!$B$5:$B$48,A5,Задачи!$G$5:$G$48) -> 23 | J5: =COUNTA('Ч1 подробно'!$A$5:$A$76) -> 72 | K5: =COUNTIF('Ч1 подробно'!$I$5:$I$76,"В работе") -> 0 | L5: =COUNTIF('Ч1 подробно'!$I$5:$I$76,"Готово") -> 0 | M5: =IF(J5=0,0,L5/J5) -> 0
A6: Человек 2 | C6: Collector, алгоритмы обнаружения A–D, хранилище ClickHouse, оценка качества (Recall/FPR) | D6: app/collector/, app/detector/, app/storage/ | E6: =COUNTIF(Задачи!$B$5:$B$48,A6) -> 13 | F6: =COUNTIFS(Задачи!$B$5:$B$48,A6,Задачи!$H$5:$H$48,"В работе") -> 0 | G6: =COUNTIFS(Задачи!$B$5:$B$48,A6,Задачи!$H$5:$H$48,"Готово") -> 0 | H6: =IF(E6=0,0,G6/E6) -> 0 | I6: =SUMIF(Задачи!$B$5:$B$48,A6,Задачи!$G$5:$G$48) -> 24 | J6: =COUNTA('Ч2 подробно'!$A$5:$A$68) -> 64 | K6: =COUNTIF('Ч2 подробно'!$I$5:$I$68,"В работе") -> 0 | L6: =COUNTIF('Ч2 подробно'!$I$5:$I$68,"Готово") -> 0 | M6: =IF(J6=0,0,L6/J6) -> 0
A7: Человек 3 | C7: FastAPI, веб-панель, аутентификация, аудит, проверки безопасности веб-приложения | D7: app/api/, app/security/, web/, tests/test_auth.py, tests/test_api.py | E7: =COUNTIF(Задачи!$B$5:$B$48,A7) -> 13 | F7: =COUNTIFS(Задачи!$B$5:$B$48,A7,Задачи!$H$5:$H$48,"В работе") -> 0 | G7: =COUNTIFS(Задачи!$B$5:$B$48,A7,Задачи!$H$5:$H$48,"Готово") -> 0 | H7: =IF(E7=0,0,G7/E7) -> 0 | I7: =SUMIF(Задачи!$B$5:$B$48,A7,Задачи!$G$5:$G$48) -> 21 | J7: =COUNTA('Ч3 подробно'!$A$5:$A$50) -> 46 | K7: =COUNTIF('Ч3 подробно'!$I$5:$I$50,"В работе") -> 0 | L7: =COUNTIF('Ч3 подробно'!$I$5:$I$50,"Готово") -> 0 | M7: =IF(J7=0,0,L7/J7) -> 0
A8: Все | B8: — | C8: Общие задачи: контракты интерфейсов, интеграция, финальный отчёт и защита | D8: docs/, README.md | E8: =COUNTIF(Задачи!$B$5:$B$48,A8) -> 4 | F8: =COUNTIFS(Задачи!$B$5:$B$48,A8,Задачи!$H$5:$H$48,"В работе") -> 0 | G8: =COUNTIFS(Задачи!$B$5:$B$48,A8,Задачи!$H$5:$H$48,"Готово") -> 0 | H8: =IF(E8=0,0,G8/E8) -> 0 | I8: =SUMIF(Задачи!$B$5:$B$48,A8,Задачи!$G$5:$G$48) -> 4 | J8: =COUNTA('Общие подробно'!$A$5:$A$16) -> 12 | K8: =COUNTIF('Общие подробно'!$I$5:$I$16,"В работе") -> 0 | L8: =COUNTIF('Общие подробно'!$I$5:$I$16,"Готово") -> 0 | M8: =IF(J8=0,0,L8/J8) -> 0
A9: Итого | E9: =SUM(E5:E8) -> 44 | F9: =SUM(F5:F8) -> 0 | G9: =SUM(G5:G8) -> 0 | H9: =IF(E9=0,0,G9/E9) -> 0 | I9: =SUM(I5:I8) -> 72 | J9: =SUM(J5:J8) -> 194 | K9: =SUM(K5:K8) -> 0 | L9: =SUM(L5:L8) -> 0 | M9: =IF(J9=0,0,L9/J9) -> 0
A11: Листы «Ч1/Ч2/Ч3/Общие подробно» содержат полную декомпозицию ТЗ; лист «Задачи» — укрупнённый план с диаграммой Ганта.

Sheet Задачи
A1: NetShield — задачи и диаграмма Ганта
A2: Легенда: синий текст = вводимые значения (недели старта/конца, статус). Черный = формулы. Ячейки Ганта заливаются автоматически по неделям старта и конца. Исполнителей можно заменить на имена через «Найти и заменить» (на листах «Задачи» и «Роли»).
J3: Недели проекта →
A4: ID | B4: Исполнитель | C4: Блок | D4: Задача | E4: Старт (нед.) | F4: Конец (нед.) | G4: Длит. (нед.) | H4: Статус | I4: Зависит от | J4: 1 | K4: 2 | L4: 3 | M4: 4 | N4: 5 | O4: 6 | P4: 7 | Q4: 8 | R4: 9 | S4: 10 | T4: 11 | U4: 12
A5: 0.1 | B5: Все | C5: Старт | D5: Согласовать контракты интерфейсов: Metrics, Decision, Rule, Event (pydantic-модели), список разрешённых действий | E5: 1 | F5: 1 | G5: =F5-E5+1 -> 1 | H5: Не начато | J5: =IF(AND(J$4>=$E5,J$4<=$F5),1,"") -> 1 | K5: =IF(AND(K$4>=$E5,K$4<=$F5),1,"") | L5: =IF(AND(L$4>=$E5,L$4<=$F5),1,"") | M5: =IF(AND(M$4>=$E5,M$4<=$F5),1,"") | N5: =IF(AND(N$4>=$E5,N$4<=$F5),1,"") | O5: =IF(AND(O$4>=$E5,O$4<=$F5),1,"") | P5: =IF(AND(P$4>=$E5,P$4<=$F5),1,"") | Q5: =IF(AND(Q$4>=$E5,Q$4<=$F5),1,"") | ... U5: =IF(AND(U$4>=$E5,U$4<=$F5),1,"")
A6: 1.1 | B6: Человек 1 | C6: Стенд | D6: Репозиторий и структура netshield/, ветки и правила git | E6: 1 | F6: 1 | G6: =F6-E6+1 -> 1 | H6: Не начато | J6: =IF(AND(J$4>=$E6,J$4<=$F6),1,"") -> 1 | K6: =IF(AND(K$4>=$E6,K$4<=$F6),1,"") | L6: =IF(AND(L$4>=$E6,L$4<=$F6),1,"") | M6: =IF(AND(M$4>=$E6,M$4<=$F6),1,"") | N6: =IF(AND(N$4>=$E6,N$4<=$F6),1,"") | O6: =IF(AND(O$4>=$E6,O$4<=$F6),1,"") | P6: =IF(AND(P$4>=$E6,P$4<=$F6),1,"") | Q6: =IF(AND(Q$4>=$E6,Q$4<=$F6),1,"") | ... U6: =IF(AND(U$4>=$E6,U$4<=$F6),1,"")
A7: 1.2 | B7: Человек 1 | C7: Стенд | D7: Развернуть стенд (ВМ или network namespaces: клиент, шлюз, backend), topology.md | E7: 1 | F7: 2 | G7: =F7-E7+1 -> 2 | H7: Не начато | J7: =IF(AND(J$4>=$E7,J$4<=$F7),1,"") -> 1 | K7: =IF(AND(K$4>=$E7,K$4<=$F7),1,"") -> 1 | L7: =IF(AND(L$4>=$E7,L$4<=$F7),1,"") | M7: =IF(AND(M$4>=$E7,M$4<=$F7),1,"") | N7: =IF(AND(N$4>=$E7,N$4<=$F7),1,"") | O7: =IF(AND(O$4>=$E7,O$4<=$F7),1,"") | P7: =IF(AND(P$4>=$E7,P$4<=$F7),1,"") | Q7: =IF(AND(Q$4>=$E7,Q$4<=$F7),1,"") | ... U7: =IF(AND(U$4>=$E7,U$4<=$F7),1,"")
A8: 1.3 | B8: Человек 1 | C8: Сеть | D8: IP forwarding, NAT, проверка интерфейсов (configure_network.sh) | E8: 2 | F8: 3 | G8: =F8-E8+1 -> 2 | H8: Не начато | I8: 1.2 | J8: =IF(AND(J$4>=$E8,J$4<=$F8),1,"") | K8: =IF(AND(K$4>=$E8,K$4<=$F8),1,"") -> 1 | L8: =IF(AND(L$4>=$E8,L$4<=$F8),1,"") -> 1 | M8: =IF(AND(M$4>=$E8,M$4<=$F8),1,"") | N8: =IF(AND(N$4>=$E8,N$4<=$F8),1,"") | O8: =IF(AND(O$4>=$E8,O$4<=$F8),1,"") | P8: =IF(AND(P$4>=$E8,P$4<=$F8),1,"") | Q8: =IF(AND(Q$4>=$E8,Q$4<=$F8),1,"") | ... U8: =IF(AND(U$4>=$E8,U$4<=$F8),1,"")
A9: 1.4 | B9: Человек 1 | C9: Firewall | D9: Базовые таблицы и цепочки nftables (configure_firewall.sh) | E9: 2 | F9: 3 | G9: =F9-E9+1 -> 2 | H9: Не начато | I9: 1.2 | J9: =IF(AND(J$4>=$E9,J$4<=$F9),1,"") | K9: =IF(AND(K$4>=$E9,K$4<=$F9),1,"") -> 1 | L9: =IF(AND(L$4>=$E9,L$4<=$F9),1,"") -> 1 | M9: =IF(AND(M$4>=$E9,M$4<=$F9),1,"") | N9: =IF(AND(N$4>=$E9,N$4<=$F9),1,"") | O9: =IF(AND(O$4>=$E9,O$4<=$F9),1,"") | P9: =IF(AND(P$4>=$E9,P$4<=$F9),1,"") | Q9: =IF(AND(Q$4>=$E9,Q$4<=$F9),1,"") | ... U9: =IF(AND(U$4>=$E9,U$4<=$F9),1,"")
A10: 1.5 | B10: Человек 1 | C10: Тесты | D10: Тесты T01–T07: TCP/UDP, порты, изоляция серверов, обход шлюза, NAT | E10: 3 | F10: 4 | G10: =F10-E10+1 -> 2 | H10: Не начато | I10: 1.3; 1.4 | J10: =IF(AND(J$4>=$E10,J$4<=$F10),1,"") | K10: =IF(AND(K$4>=$E10,K$4<=$F10),1,"") | L10: =IF(AND(L$4>=$E10,L$4<=$F10),1,"") -> 1 | M10: =IF(AND(M$4>=$E10,M$4<=$F10),1,"") -> 1 | N10: =IF(AND(N$4>=$E10,N$4<=$F10),1,"") | O10: =IF(AND(O$4>=$E10,O$4<=$F10),1,"") | P10: =IF(AND(P$4>=$E10,P$4<=$F10),1,"") | Q10: =IF(AND(Q$4>=$E10,Q$4<=$F10),1,"") | ... U10: =IF(AND(U$4>=$E10,U$4<=$F10),1,"")
A11: 1.6 | B11: Человек 1 | C11: Firewall | D11: policy.py и validation.py: политика сервера, проверка параметров правил | E11: 4 | F11: 5 | G11: =F11-E11+1 -> 2 | H11: Не начато | I11: 0.1 | J11: =IF(AND(J$4>=$E11,J$4<=$F11),1,"") | K11: =IF(AND(K$4>=$E11,K$4<=$F11),1,"") | L11: =IF(AND(L$4>=$E11,L$4<=$F11),1,"") | M11: =IF(AND(M$4>=$E11,M$4<=$F11),1,"") -> 1 | N11: =IF(AND(N$4>=$E11,N$4<=$F11),1,"") -> 1 | O11: =IF(AND(O$4>=$E11,O$4<=$F11),1,"") | P11: =IF(AND(P$4>=$E11,P$4<=$F11),1,"") | Q11: =IF(AND(Q$4>=$E11,Q$4<=$F11),1,"") | ... U11: =IF(AND(U$4>=$E11,U$4<=$F11),1,"")
A12: 1.7 | B12: Человек 1 | C12: Firewall | D12: rule_manager.py: лимиты TCP/UDP, TTL, cooldown, whitelist, атомарное обновление, откат | E12: 4 | F12: 5 | G12: =F12-E12+1 -> 2 | H12: Не начато | I12: 1.6 | J12: =IF(AND(J$4>=$E12,J$4<=$F12),1,"") | K12: =IF(AND(K$4>=$E12,K$4<=$F12),1,"") | L12: =IF(AND(L$4>=$E12,L$4<=$F12),1,"") | M12: =IF(AND(M$4>=$E12,M$4<=$F12),1,"") -> 1 | N12: =IF(AND(N$4>=$E12,N$4<=$F12),1,"") -> 1 | O12: =IF(AND(O$4>=$E12,O$4<=$F12),1,"") | P12: =IF(AND(P$4>=$E12,P$4<=$F12),1,"") | Q12: =IF(AND(Q$4>=$E12,Q$4<=$F12),1,"") | ... U12: =IF(AND(U$4>=$E12,U$4<=$F12),1,"")
A13: 1.8 | B13: Человек 1 | C13: Скрипты | D13: install.sh, secure_ssh.sh, configure_sysctl.sh | E13: 7 | F13: 8 | G13: =F13-E13+1 -> 2 | H13: Не начато | I13: 1.3 | J13: =IF(AND(J$4>=$E13,J$4<=$F13),1,"") | K13: =IF(AND(K$4>=$E13,K$4<=$F13),1,"") | L13: =IF(AND(L$4>=$E13,L$4<=$F13),1,"") | M13: =IF(AND(M$4>=$E13,M$4<=$F13),1,"") | N13: =IF(AND(N$4>=$E13,N$4<=$F13),1,"") | O13: =IF(AND(O$4>=$E13,O$4<=$F13),1,"") | P13: =IF(AND(P$4>=$E13,P$4<=$F13),1,"") -> 1 | Q13: =IF(AND(Q$4>=$E13,Q$4<=$F13),1,"") -> 1 | ... U13: =IF(AND(U$4>=$E13,U$4<=$F13),1,"")
A14: 1.9 | B14: Человек 1 | C14: Скрипты | D14: backup_config.sh, restore_config.sh, configure_service.sh (systemd) | E14: 7 | F14: 8 | G14: =F14-E14+1 -> 2 | H14: Не начато | I14: 1.7 | J14: =IF(AND(J$4>=$E14,J$4<=$F14),1,"") | K14: =IF(AND(K$4>=$E14,K$4<=$F14),1,"") | L14: =IF(AND(L$4>=$E14,L$4<=$F14),1,"") | M14: =IF(AND(M$4>=$E14,M$4<=$F14),1,"") | N14: =IF(AND(N$4>=$E14,N$4<=$F14),1,"") | O14: =IF(AND(O$4>=$E14,O$4<=$F14),1,"") | P14: =IF(AND(P$4>=$E14,P$4<=$F14),1,"") -> 1 | Q14: =IF(AND(Q$4>=$E14,Q$4<=$F14),1,"") -> 1 | ... U14: =IF(AND(U$4>=$E14,U$4<=$F14),1,"")
A15: 1.10 | B15: Человек 1 | C15: Тесты | D15: Тесты T08–T10: перезапуск шлюза и Python, ошибка конфигурации | E15: 7 | F15: 8 | G15: =F15-E15+1 -> 2 | H15: Не начато | I15: 1.8; 1.9 | J15: =IF(AND(J$4>=$E15,J$4<=$F15),1,"") | K15: =IF(AND(K$4>=$E15,K$4<=$F15),1,"") | L15: =IF(AND(L$4>=$E15,L$4<=$F15),1,"") | M15: =IF(AND(M$4>=$E15,M$4<=$F15),1,"") | N15: =IF(AND(N$4>=$E15,N$4<=$F15),1,"") | O15: =IF(AND(O$4>=$E15,O$4<=$F15),1,"") | P15: =IF(AND(P$4>=$E15,P$4<=$F15),1,"") -> 1 | Q15: =IF(AND(Q$4>=$E15,Q$4<=$F15),1,"") -> 1 | ... U15: =IF(AND(U$4>=$E15,U$4<=$F15),1,"")
A16: 1.11 | B16: Человек 1 | C16: Автоматика | D16: Включить автоприменение правил, испытания фильтрации (раздел 9.4) | E16: 9 | F16: 9 | G16: =F16-E16+1 -> 1 | H16: Не начато | I16: 1.7; 2.6 | J16: =IF(AND(J$4>=$E16,J$4<=$F16),1,"") | K16: =IF(AND(K$4>=$E16,K$4<=$F16),1,"") | L16: =IF(AND(L$4>=$E16,L$4<=$F16),1,"") | M16: =IF(AND(M$4>=$E16,M$4<=$F16),1,"") | N16: =IF(AND(N$4>=$E16,N$4<=$F16),1,"") | O16: =IF(AND(O$4>=$E16,O$4<=$F16),1,"") | P16: =IF(AND(P$4>=$E16,P$4<=$F16),1,"") | Q16: =IF(AND(Q$4>=$E16,Q$4<=$F16),1,"") | ... U16: =IF(AND(U$4>=$E16,U$4<=$F16),1,"")
A17: 1.12 | B17: Человек 1 | C17: Производительность | D17: Замеры в 4 режимах, ≥5 повторов, результаты в CSV | E17: 10 | F17: 10 | G17: =F17-E17+1 -> 1 | H17: Не начато | I17: 1.11 | J17: =IF(AND(J$4>=$E17,J$4<=$F17),1,"") | K17: =IF(AND(K$4>=$E17,K$4<=$F17),1,"") | L17: =IF(AND(L$4>=$E17,L$4<=$F17),1,"") | M17: =IF(AND(M$4>=$E17,M$4<=$F17),1,"") | N17: =IF(AND(N$4>=$E17,N$4<=$F17),1,"") | O17: =IF(AND(O$4>=$E17,O$4<=$F17),1,"") | P17: =IF(AND(P$4>=$E17,P$4<=$F17),1,"") | Q17: =IF(AND(Q$4>=$E17,Q$4<=$F17),1,"") | ... U17: =IF(AND(U$4>=$E17,U$4<=$F17),1,"")
A18: 1.13 | B18: Человек 1 | C18: Скрипты | D18: check_security.sh, исправления по результатам стенда | E18: 11 | F18: 11 | G18: =F18-E18+1 -> 1 | H18: Не начато | I18: 1.12 | J18: =IF(AND(J$4>=$E18,J$4<=$F18),1,"") | K18: =IF(AND(K$4>=$E18,K$4<=$F18),1,"") | L18: =IF(AND(L$4>=$E18,L$4<=$F18),1,"") | M18: =IF(AND(M$4>=$E18,M$4<=$F18),1,"") | N18: =IF(AND(N$4>=$E18,N$4<=$F18),1,"") | O18: =IF(AND(O$4>=$E18,O$4<=$F18),1,"") | P18: =IF(AND(P$4>=$E18,P$4<=$F18),1,"") | Q18: =IF(AND(Q$4>=$E18,Q$4<=$F18),1,"") | ... U18: =IF(AND(U$4>=$E18,U$4<=$F18),1,"")
A19: 1.14 | B19: Человек 1 | C19: Документация | D19: Инструкция по установке, резервному копированию и восстановлению | E19: 12 | F19: 12 | G19: =F19-E19+1 -> 1 | H19: Не начато | I19: 1.13 | J19: =IF(AND(J$4>=$E19,J$4<=$F19),1,"") | K19: =IF(AND(K$4>=$E19,K$4<=$F19),1,"") | L19: =IF(AND(L$4>=$E19,L$4<=$F19),1,"") | M19: =IF(AND(M$4>=$E19,M$4<=$F19),1,"") | N19: =IF(AND(N$4>=$E19,N$4<=$F19),1,"") | O19: =IF(AND(O$4>=$E19,O$4<=$F19),1,"") | P19: =IF(AND(P$4>=$E19,P$4<=$F19),1,"") | Q19: =IF(AND(Q$4>=$E19,Q$4<=$F19),1,"") | ... U19: =IF(AND(U$4>=$E19,U$4<=$F19),1,"") -> 1
... A48: 0.4 | B48: Все | C48: Финал | D48: Финальный отчёт и защита проекта | E48: 12 | F48: 12 | G48: =F48-E48+1 -> 1 | H48: Не начато | I48: 1.14; 2.13; 3.13 | J48: =IF(AND(J$4>=$E48,J$4<=$F48),1,"") | K48: =IF(AND(K$4>=$E48,K$4<=$F48),1,"") | L48: =IF(AND(L$4>=$E48,L$4<=$F48),1,"") | M48: =IF(AND(M$4>=$E48,M$4<=$F48),1,"") | N48: =IF(AND(N$4>=$E48,N$4<=$F48),1,"") | O48: =IF(AND(O$4>=$E48,O$4<=$F48),1,"") | P48: =IF(AND(P$4>=$E48,P$4<=$F48),1,"") | Q48: =IF(AND(Q$4>=$E48,Q$4<=$F48),1,"") | ... U48: =IF(AND(U$4>=$E48,U$4<=$F48),1,"") -> 1

Sheet Ч1 подробно
A1: Человек 1 — Linux, сеть, firewall, Rule Manager, скрипты, стенд, производительность
A2: Все пункты взяты из ТЗ; в столбце «Раздел ТЗ» указан номер раздела. Синий = вводимые значения (недели, статус, примечание).
A4: № | B4: Раздел ТЗ | C4: Блок | D4: Задача (подробно) | E4: Результат / критерий готовности | F4: Файл / модуль | G4: Нед. старт | H4: Нед. конец | I4: Статус | J4: Примечание
A5: Ч1-01 | B5: 9.1 | C5: Стенд | D5: Развернуть лабораторный стенд на собственных ВМ (KVM/VirtualBox) или Linux network namespaces: клиент/генератор нагрузки, шлюз, backend (Web + игровой сервис). Сеть изолирована, чужие сети и публичные серверы не затрагиваются. | E5: Стенд поднимается по инструкции повторяемо | F5: lab/topology.md | G5: 1 | H5: 2 | I5: Не начато
A6: Ч1-02 | B6: 9.1 | C6: Стенд | D6: Установить и проверить инструменты: nftables, conntrack, tcpdump, Wireshark, iperf3, pytest, wrk или k6, тестовый UDP-генератор с ограничением скорости. Зафиксировать версии. | E6: Все инструменты запускаются на стенде | F6: lab/ | G6: 1 | H6: 2 | I6: Не начато
A7: Ч1-03 | B7: 9.1 | C7: Стенд | D7: Поднять на backend тестовые сервисы: Web (HTTP) и UDP-сервис, имитирующий игровой. | E7: Сервисы отвечают через шлюз | F7: lab/ | G7: 2 | H7: 3 | I7: Не начато
A8: Ч1-04 | B8: 13 | C8: Стенд | D8: Создать Git-репозиторий и структуру netshield/ (app, web, scripts, tests, lab, deploy, docs), pyproject.toml, .env.example, README.md. | E8: Структура соответствует разделу 13 ТЗ | F8: корень репозитория | G8: 1 | H8: 1 | I8: Не начато
A9: Ч1-05 | B9: 9.3 | C9: Стенд | D9: Описать формат сценария испытаний: длительность, профиль нагрузки, целевой IP/порт, протокол, ожидаемое поведение, критерии прохождения. | E9: Шаблон принят всей командой | F9: lab/scenarios.md | G9: 2 | H9: 3 | I9: Не начато
A10: Ч1-06 | B10: 4.2 | C10: Маршрутизация и NAT | D10: Включить и проверить IP forwarding (IPv4; IPv6 — если включён в конфигурации), убедиться, что значение сохраняется после перезагрузки. | E10: sysctl net.ipv4.ip_forward=1 после reboot | F10: scripts/configure_network.sh | G10: 2 | H10: 3 | I10: Не начато
A11: Ч1-07 | B11: 4.2 | C11: Маршрутизация и NAT | D11: Проверить интерфейсы и маршруты шлюза (внешний и внутренний), вывести понятную ошибку при отсутствии интерфейса. | E11: Скрипт не падает на отсутствующем интерфейсе | F11: scripts/configure_network.sh | G11: 2 | H11: 3 | I11: Не начато
A12: Ч1-08 | B12: 4.2 | C12: Маршрутизация и NAT | D12: Обеспечить пересылку TCP- и UDP-трафика между интерфейсами шлюза. | E12: Тесты T01 и T02 проходят | F12: nftables | G12: 2 | H12: 3 | I12: Не начато
A13: Ч1-09 | B13: 4.2 | C13: Маршрутизация и NAT | D13: Настроить NAT (DNAT/SNAT/masquerade) под выбранную топологию и корректный обратный маршрут ответов. | E13: Ответы доходят до клиента (T07) | F13: nftables | G13: 3 | H13: 4 | I13: Не начато
A14: Ч1-10 | B14: 4.2 / 9.2 | C14: Маршрутизация и NAT | D14: Ограничить прямой доступ к защищаемому серверу в обход шлюза: правила на шлюзе + конфигурация backend (игровой порт разрешён только с адреса шлюза или из доверенной внутренней сети). | E14: Прямой доступ извне невозможен (T06) | F14: nftables, настройка backend | G14: 3 | H14: 4 | I14: Не начато
A15: Ч1-11 | B15: 4.1 | C15: Маршрутизация и NAT | D15: Обеспечить поддержку нескольких защищаемых серверов и портов с независимыми правилами: изменение одного сервера не меняет политику других. | E15: Тесты T03 и T04 проходят | F15: nftables, policy.py | G15: 4 | H15: 5 | I15: Не начато
A16: Ч1-12 | B16: 4.2 | C16: nftables | D16: Создать базовые таблицы и цепочки nftables (input, forward, prerouting, postrouting), политику по умолчанию и правила для established/related. | E16: Базовый набор загружается без ошибок | F16: scripts/configure_firewall.sh | G16: 2 | H16: 3 | I16: Не начато
... A76: Ч1-72 | B76: 13 | C76: Документация | D76: Написать инструкцию по установке, настройке, резервному копированию и восстановлению; описание стенда (topology.md). | E76: Раздел в docs/ готов | F76: docs/, lab/ | G76: 12 | H76: 12 | I76: Не начато

Sheet Ч2 подробно
A1: Человек 2 — Collector, Detector, ClickHouse, оценка качества
A2: Все пункты взяты из ТЗ; в столбце «Раздел ТЗ» указан номер раздела. Синий = вводимые значения (недели, статус, примечание).
A4: № | B4: Раздел ТЗ | C4: Блок | D4: Задача (подробно) | E4: Результат / критерий готовности | F4: Файл / модуль | G4: Нед. старт | H4: Нед. конец | I4: Статус | J4: Примечание
A5: Ч2-01 | B5: 5 | C5: Collector | D5: sources.py: общий интерфейс источника метрик; периодический опрос каждые 1 с (интервал настраивается); контроль точного интервала Δt. | E5: Опрос идёт без накопления задержки | F5: app/collector/sources.py | G5: 2 | H5: 3 | I5: Не начато
A6: Ч2-02 | B6: 5.2 | C6: Collector | D6: interfaces.py: чтение счётчиков /sys/class/net/<iface>/statistics (rx/tx bytes и packets, drops, errors). | E6: Счётчики читаются по всем интерфейсам | F6: app/collector/interfaces.py | G6: 2 | H6: 3 | I6: Не начато
A7: Ч2-03 | B7: 5.3 | C7: Collector | D7: Расчёт скоростей: PPS = ΔP/Δt, bps = ΔB·8/Δt для входящего и исходящего направлений. | E7: Значения совпадают с iperf3 | F7: app/collector/ | G7: 2 | H7: 3 | I7: Не начато
A8: Ч2-04 | B8: 5.3 | C8: Collector | D8: Обработка сброса счётчиков (значение уменьшилось), перезапуска интерфейса и отсутствия данных. | E8: Нет отрицательных скоростей и скачков | F8: app/collector/ | G8: 2 | H8: 3 | I8: Не начато
A9: Ч2-05 | B9: 5.3 / A11 | C9: Collector | D9: Отсутствие метрики не считать нулевым трафиком: помечать «нет данных», писать ошибку сбора в system_status. | E9: Тест A11 проходит | F9: app/collector/, system_status | G9: 3 | H9: 4 | I9: Не начато
A10: Ч2-06 | B10: 5.2 | C10: Collector | D10: nftables.py: чтение счётчиков и состояния правил nftables (nft -j), расчёт дельт по защищаемым серверам, портам и направлениям. | E10: Метрики по каждому серверу | F10: app/collector/nftables.py | G10: 7 | H10: 8 | I10: Не начато
A11: Ч2-07 | B11: 5.2 | C11: Collector | D11: conntrack.py: количество записей conntrack (count/max), скорость появления новых соединений (tcp_new). | E11: conntrack_count и tcp_new в метриках | F11: app/collector/conntrack.py | G11: 7 | H11: 8 | I11: Не начато
A12: Ч2-08 | B12: 5.2 | C12: Collector | D12: Системные метрики Linux: CPU, RAM, load average, состояние служб. | E12: Данные попадают в system_status | F12: app/collector/ | G12: 7 | H12: 8 | I12: Не начато
A13: Ч2-09 | B13: 5.1 / 8 | C13: Collector | D13: Формировать метрики по каждому серверу: in/out bytes, in/out PPS, in/out bps, tcp_new, udp_pps, conntrack_count. | E13: Поля соответствуют таблицам traffic_metrics и connection_metrics | F13: app/collector/ | G13: 3 | H13: 4 | I13: Не начато
A14: Ч2-10 | B14: 5.2 / 6.4 | C14: Collector | D14: Детализация по источникам (per-IP): новые TCP-соединения, UDP pps, обращения к порту, число новых источников за интервал — через наборы nftables/conntrack; включается только при необходимости. | E14: Per-IP метрики доступны Detector | F14: app/collector/nftables.py | G14: 7 | H14: 8 | I14: Не начато
A15: Ч2-11 | B15: 5.2 | C15: Collector | D15: Опционально: ограниченный захват заголовков пакетов (только при необходимости, с лимитом нагрузки). | E15: Нагрузка на CPU измерена | F15: app/collector/ | G15: 8 | H15: 9 | I15: Не начато
A16: Ч2-12 | B16: 8.4 | C16: Collector | D16: Присваивать каждому измерению уникальный идентификатор для корректной дедупликации при повторной доставке пакета. | E16: Повторная запись не искажает агрегаты | F16: app/collector/ | G16: 4 | H16: 4 | I16: Не начато
... A68: Ч2-64 | B68: 13 | C68: Документация | D68: Таблицы качества обнаружения, описание алгоритмов и параметров, ограничения подхода. | E68: Раздел в docs/ готов | F68: docs/ | G68: 12 | H68: 12 | I68: Не начато

Sheet Ч3 подробно
A1: Человек 3 — API, веб-панель, аутентификация, аудит, тесты безопасности
A2: Все пункты взяты из ТЗ; в столбце «Раздел ТЗ» указан номер раздела. Синий = вводимые значения (недели, статус, примечание).
A4: № | B4: Раздел ТЗ | C4: Блок | D4: Задача (подробно) | E4: Результат / критерий готовности | F4: Файл / модуль | G4: Нед. старт | H4: Нед. конец | I4: Статус | J4: Примечание
A5: Ч3-01 | B5: 12 | C5: API | D5: Каркас FastAPI: main.py, подключение роутеров, конфигурация из окружения (.env), структура модулей. | E5: Приложение запускается | F5: app/main.py | G5: 1 | H5: 1 | I5: Не начато
A6: Ч3-02 | B6: 11 | C6: API | D6: Централизованная обработка ошибок и логирование без раскрытия секретов. | E6: Секретов нет в логах | F6: app/main.py | G6: 2 | H6: 3 | I6: Не начато
A7: Ч3-03 | B7: 7.3 | C7: API | D7: Валидация всех входных данных (pydantic): IPv4/IPv6, порт 1–65535, протокол TCP/UDP/оба, тип сервиса. | E7: Некорректный ввод отклоняется | F7: app/api/ | G7: 2 | H7: 3 | I7: Не начато
A8: Ч3-04 | B8: 4.1 | C8: API | D8: api/servers.py: добавление и изменение защищаемого сервера (название, IP, порты, протокол, тип сервиса, внутренний IP и порт, статус защиты, профиль). | E8: CRUD работает | F8: app/api/servers.py | G8: 4 | H8: 5 | I8: Не начато
A9: Ч3-05 | B9: 4.1 | C9: API | D9: Несколько серверов с независимыми правилами: изменение одного не меняет остальные. | E9: Проверено тестом | F9: app/api/servers.py | G9: 4 | H9: 5 | I9: Не начато
A10: Ч3-06 | B10: 7.2 | C10: API | D10: api/metrics.py: график трафика и соединений по серверу и диапазону (5 мин, 1 ч, 24 ч, 7 дн) с агрегированием и ограничением строк. | E10: Ответ ограничен по размеру | F10: app/api/metrics.py | G10: 5 | H10: 6 | I10: Не начато
A11: Ч3-07 | B11: 7.2 | C11: API | D11: Возвращать явный признак «нет данных» / «сбор недоступен», а не нулевые значения. | E11: API не подменяет пропуск нулём | F11: app/api/metrics.py | G11: 5 | H11: 6 | I11: Не начато
A12: Ч3-08 | B12: 7.2 | C12: API | D12: api/events.py: список событий с фильтрами (сервер, время, протокол, уровень риска, тип действия) и пагинацией. | E12: Фильтры работают | F12: app/api/events.py | G12: 7 | H12: 8 | I12: Не начато
A13: Ч3-09 | B13: 7.2 | C13: API | D13: api/rules.py: список активных, временных и постоянных правил; применение разрешённого правила; снятие правила. | E13: Только предусмотренные операции | F13: app/api/rules.py | G13: 7 | H13: 8 | I13: Не начато
A14: Ч3-10 | B14: 7.2 | C14: API | D14: API настроек: пороги, интервалы сбора, режим обнаружения (наблюдение/авто), включение и отключение автодействий. | E14: Изменения записываются в аудит | F14: app/api/ | G14: 7 | H14: 8 | I14: Не начато
A15: Ч3-11 | B15: 7.2 | C15: API | D15: API безопасности и статуса: состояние служб, ошибки конфигурации, system_status. | E15: Данные для страницы «Безопасность» | F15: app/api/ | G15: 8 | H15: 9 | I15: Не начато
A16: Ч3-12 | B16: 7.3 / 11 | C16: API | D16: Взаимодействие с Rule Manager через ограниченный интерфейс; выполнение произвольных shell-команд из запросов невозможно. | E16: Тест 9.6: shell-команда отклонена | F16: app/api/rules.py | G16: 7 | H16: 8 | I16: Не начато
... A50: Ч3-46 | B50: 13 | C50: Документация | D50: Сборка единой документации проекта и анализ ограничений и направлений развития. | E50: docs/ собрана | F50: docs/ | G50: 12 | H50: 12 | I50: Не начато

Sheet Общие подробно
A1: Общие задачи всей команды
A2: Все пункты взяты из ТЗ; в столбце «Раздел ТЗ» указан номер раздела. Синий = вводимые значения (недели, статус, примечание).
A4: № | B4: Раздел ТЗ | C4: Блок | D4: Задача (подробно) | E4: Результат / критерий готовности | F4: Файл / модуль | G4: Нед. старт | H4: Нед. конец | I4: Статус | J4: Примечание
A5: ОБ-01 | B5: 3 / 13 | C5: Контракты | D5: Согласовать форматы данных между модулями: Metrics, Decision, Rule, Event (pydantic) и список разрешённых действий; принцип «Python не обрабатывает каждый пакет». | E5: Модели закоммичены | F5: app/storage/models.py | G5: 1 | H5: 1 | I5: Не начато
A6: ОБ-02 | B6: 13 | C6: Организация | D6: Договориться о ветках, ревью merge request и регулярных встречах. | E6: Правила записаны в README | F6: README.md | G6: 1 | H6: 1 | I6: Не начато
A7: ОБ-03 | B7: 6.6 | C7: Интеграция | D7: Сквозная интеграция Collector → Detector → Rule Manager → API → панель в режиме наблюдения. | E7: Событие видно в панели | F7: весь проект | G7: 6 | H7: 6 | I7: Не начато
A8: ОБ-04 | B8: 10 | C8: Интеграция | D8: Включить автоматический режим и проверить главный критерий: аномалия → событие в панели → автоматическое ограниченное правило; при остановке Python базовая фильтрация работает. | E8: Главный критерий ТЗ выполнен | F8: весь проект | G8: 9 | H8: 9 | I8: Не начато
A9: ОБ-05 | B9: 10 | C9: Интеграция | D9: Повторить ключевые тесты после исправлений (повторяемость). | E9: Результаты сопоставимы | F9: lab/results/ | G9: 11 | H9: 11 | I9: Не начато
A10: ОБ-06 | B10: 2 / 13 | C10: Документация | D10: Описать границы проекта и ограничения: не защищает от перегрузки внешнего канала, не заменяет глобальную защиту, не анализирует каждый пакет в Python, IP ≠ пользователь (NAT). | E10: Раздел «Ограничения» | F10: docs/ | G10: 12 | H10: 12 | I10: Не начато
A11: ОБ-07 | B11: 13 | C11: Документация | D11: Описать направления развития: несколько шлюзов, расширенный сбор метрик, настройка алгоритмов. | E11: Раздел «Развитие» | F11: docs/ | G11: 12 | H11: 12 | I11: Не начато
A12: ОБ-08 | B12: 13 | C12: Итоговый комплект | D12: Исходный код Python-приложения; скрипты установки и безопасности Linux; конфигурация маршрутизации и nftables. | E12: Всё в репозитории | F12: репозиторий | G12: 12 | H12: 12 | I12: Не начато
A13: ОБ-09 | B13: 13 | C13: Итоговый комплект | D13: Веб-панель; алгоритмы обнаружения; автоматическое применение правил; автотесты основных модулей. | E13: Всё в репозитории | F13: репозиторий | G13: 12 | H13: 12 | I13: Не начато
A14: ОБ-10 | B14: 13 | C14: Итоговый комплект | D14: Описание стенда и сценариев; таблицы измерений производительности и качества; инструкция по установке, настройке, резервному копированию и восстановлению. | E14: Всё в docs/ и lab/ | F14: docs/, lab/ | G14: 12 | H14: 12 | I14: Не начато
A15: ОБ-11 | B15: 13 | C15: Защита | D15: Подготовить демонстрацию: запуск стенда, нормальный трафик, контролируемая аномалия, событие в панели, автоправило. | E15: Репетиция демо пройдена | F15: — | G15: 12 | H15: 12 | I15: Не начато
A16: ОБ-12 | B16: 13 | C16: Защита | D16: Подготовить итоговый отчёт и презентацию для защиты. | E16: Отчёт и слайды готовы | F16: docs/ | G16: 12 | H16: 12 | I16: Не начато

Sheet План по неделям
A1: План по неделям (12 недель)
A3: Недели | B3: Этап | C3: Человек 1 | D3: Человек 2 | E3: Человек 3
A4: 1 | B4: Старт | C4: Стенд, репозиторий, структура netshield/ | D4: Схема ClickHouse, модели метрик | E4: Каркас FastAPI, макеты страниц панели
A5: 1 (вместе) | B5: Контракты | C5: Согласовать Metrics, Decision, Rule, Event и список разрешённых действий | D5: То же | E5: То же
A6: 2–3 | B6: Основа | C6: Forwarding, NAT, базовые таблицы nftables, тесты T01–T07 | D6: Collector по интерфейсам, PPS/bps, запись в ClickHouse батчами | E6: Auth, сессии, таблица users, базовые API серверов
A7: 4–5 | B7: Ядро | C7: rule_manager, validation, rate limit, TTL и снятие правил | D7: Алгоритмы A и B, scoring, подтверждение интервалов, cooldown | E7: CRUD серверов и портов, страницы «Серверы», «Трафик», графики
A8: 6 | B8: Первая интеграция | C8: Collector → Detector → Rule Manager в режиме наблюдения | D8: То же | E8: Панель показывает реальные метрики и события
A9: 7–8 | B9: Расширение | C9: Скрипты безопасности, backup/restore, systemd, T08–T10 | D9: Алгоритмы C и D, conntrack и per-IP счётчики, whitelist | E9: События, правила, настройки, аудит, фильтры, test_api
A10: 9 | B10: Автоматический режим | C10: Автоприменение правил, тесты раздела 9.4 | D10: Калибровка порогов и шкалы риска | E10: Страница «Безопасность», проверки 9.6
A11: 10 | B11: Испытания | C11: Замеры производительности (4 режима × ≥5 повторов, CSV) | D11: Сценарии A01–A12, Recall, FPR | E11: Тесты авторизации, CSRF, некорректного ввода
A12: 11 | B12: Исправления | C12: Баги по результатам стенда, check_security.sh | D12: Баги и перекалибровка | E12: Баги UI/API, полировка
A13: 12 | B13: Финал | C13: Инструкция установки и восстановления | D13: Таблицы качества обнаружения | E13: Сборка документации, анализ ограничений, демо

Sheet Контрольные точки
A1: Контрольные точки и рекомендации
A3: Неделя | B3: Контрольная точка | C3: Критерий выполнения | D3: Статус
A4: 1 | B4: Контракты интерфейсов согласованы | C4: Описаны и закоммичены модели Metrics, Decision, Rule, Event; все работают с заглушками | D4: Не начато
A5: 6 | B5: Сквозной сценарий | C5: Аномалия на одном пороге → событие → отображение в панели (режим наблюдения) | D5: Не начато
A6: 9 | B6: Главный критерий ТЗ | C6: Контролируемая аномалия, событие в панели, автоматическое правило; защита работает при остановленном Python | D6: Не начато
A7: 10 | B7: Испытания завершены | C7: Тесты T01–T12, A01–A12, замеры производительности и качества выполнены | D7: Не начато
A8: 12 | B8: Финальная сдача | C8: Документация, таблицы измерений, отчёт, демо-сценарий готовы | D8: Не начато
A11: Рекомендации
A12: • | B12: Контракты интерфейсов на первой неделе — главное условие параллельной работы (используйте mock-заглушки).
A13: • | B13: Алгоритмы C и D и детализация по IP самые рискованные: при нехватке времени достаточно A + B + режим наблюдения, остальное описать как направления развития.
A14: • | B14: Git: ветки по слоям, merge request с ревью от соседа по интеграции (1↔2, 2↔3).
A15: • | B15: Сроки (12 недель) — допущение; при другой длительности измените недели старта и конца на листе «Задачи».
